{
	"pr_telemetry":	{
		"cabin_heating":	false,
		"cabin_cooling":	true,
		"co2_scrubber":	true,
		"lights_on":	true,
		"brakes":	false,
		"throttle":	10,
		"steering":	-0.4,
		"rover_pos_x":	-5687.100098,
		"rover_pos_y":	-10900.5,
		"rover_pos_z":	1397.800049,
		"heading":	119.700005,
		"pitch":	-1.9,
		"roll":	-12.400001,
		"distance_traveled":	951.5,
		"speed":	0,
		"sunlight":	0.392157,
		"surface_incline":	10.3,
		"lidar":	[0, 243.79, -1, 484.65, -1, 177.28, 206.13, 449.54, 545.5, 668.12, 226.61, 235.74, 925.38, 928.39, -1, -1, -1],
		"oxygen_storage":	100,
		"oxygen_pressure":	0,
		"cabin_pressure":	4,
		"cabin_temperature":	0,
		"external_temp":	0,
		"coolant_pressure":	500,
		"coolant_storage":	0,
		"primary_battery_level":	0,
		"secondary_battery_level":	100,
		"rover_elapsed_time":	0,
		"sim_running":	false,
		"dust_connected":	false,
		"distance_from_base":	0,
		"oxygen_tank":	100,
		"battery_level":	0,
		"fan_pri_rpm":	0,
		"fan_sec_rpm":	0,
		"scrubber_a_co2_storage":	0,
		"scrubber_b_co2_storage":	0,
		"cabin_temperature_target":	0
	}
}